ip2whois/__init__.py
ip2whois/api.py
IP2WHOIS-2.2.5.dist-info/LICENSE.txt
IP2WHOIS-2.2.5.dist-info/METADATA
IP2WHOIS-2.2.5.dist-info/WHEEL
IP2WHOIS-2.2.5.dist-info/top_level.txt
IP2WHOIS-2.2.5.dist-info/RECORD
